<?xml version="1.0" encoding="utf-8"?><page><controles><_404s><Erro404 ID="erro_404"><CssComponente><![CDATA[]]></CssComponente><Erro404HTML><![CDATA[<h1> testes de erro 404 via eCMS</h1>]]></Erro404HTML></Erro404></_404s><Banners><Banner ID="Fullzao" /></Banners><CaixaPesquisas><CaixaPesquisa ID="Busca_erro"><CaixaPesquisaHTML><![CDATA[<fieldset>
    <h4>Pesquise o que você deseja aqui</h4>
    <label>
        [A0] <a href="[A2]"><img src="imagens/bt_busca_erro.png?1" alt="Buscar" /></a>
    </label>
</fieldset>]]></CaixaPesquisaHTML><CssComponente><![CDATA[]]></CssComponente></CaixaPesquisa></CaixaPesquisas><Links><Link ID="Voltar_inicial_erro"><Destino value="Nenhum" /><EnderecoLinkExterno value="" /><Imagem value="" /><PaginaLoja value="Default" /><Parametros value="" /><Target value="MesmaPagina" /><Texto value="Se preferir, clique aqui para voltar para à página inicial" /><UsarHTTPS value="False" /></Link></Links><ScriptRazors><ScriptRazor ID="titlePage"><ScriptRazorHTML><![CDATA[@TemplateSettings.main_storeName]]></ScriptRazorHTML></ScriptRazor><ScriptRazor ID="title" /><ScriptRazor ID="favicon"><ScriptRazorHTML><![CDATA[<link rel="shortcut icon" href="imagens/@TemplateSettings.main_faviIcon?2" />]]></ScriptRazorHTML></ScriptRazor><ScriptRazor ID="custom_prog01"><ScriptRazorHTML><![CDATA[@TemplateSettings.custom_prog01]]></ScriptRazorHTML></ScriptRazor></ScriptRazors></controles></page>